{
	"i18n": true,
	"type": "panel",
	"items": {
		"username": {
			"type": "text",
			"label": "username",
			"newLine": true,
			"xs": 12,
			"sm": 12,
			"md": 6,
			"lg": 4,
			"xl": 4
		},
		"password": {
			"type": "password",
			"label": "password",
			"newLine": true,
			"xs": 12,
			"sm": 12,
			"md": 6,
			"lg": 4,
			"xl": 4
		},
		"pollingInterval": {
			"type": "number",
			"label": "pollingInterval",
			"min": 5,
			"max": 300,
			"newLine": true,
			"xs": 12,
			"sm": 12,
			"md": 6,
			"lg": 4,
			"xl": 4
		}
	}
}
